Construct/Construction.py
Construct/__init__.py
Data_Construct-0.0.1.dist-info/LICENSE.txt
Data_Construct-0.0.1.dist-info/METADATA
Data_Construct-0.0.1.dist-info/WHEEL
Data_Construct-0.0.1.dist-info/top_level.txt
Data_Construct-0.0.1.dist-info/RECORD
